{
    "mode": "train",
    "output_dir": "results",
    "model_path": null,
    "episodes": 3000,
    "restart": false,
    "max_steps": 600,
    "batch_size": 256,
    "memory_size": 500000,
    "gamma": 0.99,
    "epsilon": 1.0,
    "epsilon_min": 0.01,
    "epsilon_decay": 0.997,
    "learning_rate": 0.0003,
    "update_target_freq": 10,
    "render": false,
    "eval_freq": 50,
    "eval_episodes": 5,
    "seed": 42,
    "cpu_threads": 8,
    "enable_xla": true,
    "mixed_precision": true,
    "batch_norm": true,
    "save_interval": 50,
    "prefetch_batches": 6,
    "parallel_envs": 1,
    "performance_monitor": true,
    "gradient_clip": 1.0,
    "dropout": 0.1
}